gitremote.py
setup.py
GitRemote.egg-info/SOURCES.txt
gitremote.egg-info/PKG-INFO
gitremote.egg-info/SOURCES.txt
gitremote.egg-info/dependency_links.txt
gitremote.egg-info/entry_points.txt
gitremote.egg-info/not-zip-safe
gitremote.egg-info/requires.txt
gitremote.egg-info/top_level.txt