Metadata-Version: 1.1
Name: GitRemote
Version: 0.1.0
Summary: Simple tool to add git remotes effortlessly
Home-page: http://github.com/mardix/gitremote/
Author: Mardix
Author-email: mardix@pylot.io
License: MIT
Download-URL: http://github.com/mardix/gitremote/tarball/master
Keywords: git remote
Platform: any
Classifier: Environment :: Web Environment
Classifier: Intended Audience :: Developers
Classifier: License :: OSI Approved :: BSD License
Classifier: Operating System :: OS Independent
Classifier: Programming Language :: Python
Classifier: Programming Language :: Python :: 2
Classifier: Programming Language :: Python :: 2.6
Classifier: Programming Language :: Python :: 2.7
Classifier: Programming Language :: Python :: 3
Classifier: Programming Language :: Python :: 3.3
Classifier: Topic :: Internet :: WWW/HTTP :: Dynamic Content
Classifier: Topic :: Software Development :: Libraries :: Python Modules
